atila/Atila.py
atila/__init__.py
atila/apidoc.py
atila/authorizer.py
atila/cookie.py
atila/events.py
atila/mbox.py
atila/named_session.py
atila/pytest_hooks.py
atila/secured_cookie_value.py
atila/session.py
atila/app/__init__.py
atila/app/auth.py
atila/app/decorators.py
atila/app/deprecated.py
atila/app/events.py
atila/app/mixin.py
atila/app/parameters.py
atila/app/router.py
atila/app/services.py
atila/app/template_engine.py
atila/app/testutils.py
atila/collabo/__init__.py
atila/collabo/requests.py
atila/collabo/django/__init__.py
atila/collabo/django/admin.py
atila/collabo/django/fields.py
atila/collabo/django/manage.py
atila/collabo/django/model.py
atila/collabo/django/utils.py
atila/collabo/django/commands/__init__.py
atila/collabo/django/commands/_utils.py
atila/collabo/django/commands/describe_models.py
atila/collabo/django/commands/export_models.py
atila/collectors/__init__.py
atila/collectors/grpc_collector.py
atila/collectors/multipart_collector.py
atila/collectors/stream_collector.py
atila/collectors/websocket_collector.py
atila/executors/__init__.py
atila/executors/grpc_executor.py
atila/executors/jsonrpc_executor.py
atila/executors/stream_executor.py
atila/executors/ws_executor.py
atila/executors/wsgi_executor.py
atila/executors/xmlrpc_executor.py
atila/patches/__init__.py
atila/patches/jinjapatch.py
atila/patches/skitaipatch.py
atila/was/__init__.py
atila/was/output_stream.py
atila/was/piped_process.py
atila-0.27.2.dist-info/licenses/LICENSE
atila-0.27.2.dist-info/METADATA
atila-0.27.2.dist-info/WHEEL
atila-0.27.2.dist-info/top_level.txt
atila-0.27.2.dist-info/RECORD
